[
    {"id": "", "text": ""},
    {"id": "Assamese", "text": "Assamese"},
    {"id": "Awadhi", "text": "Awadhi"},
    {"id": "Bajjika", "text": "Bajjika"},
    {"id": "Bangla", "text": "Bangla"},
    {"id": "Bhojpuri", "text": "Bhojpuri"},
    {"id": "Bodo", "text": "Bodo"},
    {"id": "Braj", "text": "Braj"},
    {"id": "Bundeli", "text": "Bundeli"},
    {"id": "Chokri", "text": "Chokri"},
    {"id": "English", "text": "English"},
    {"id": "Gujarati", "text": "Gujarati"},
    {"id": "Haryanvi", "text": "Haryanvi"},
    {"id": "Hindi", "text": "Hindi"},
    {"id": "Kannada", "text": "Kannada"},
    {"id": "Khortha", "text": "Khortha"},
    {"id": "Konkani", "text": "Konkani"},
    {"id": "KokBorok", "text": "Kok Borok"},
    {"id": "Magahi", "text": "Magahi"},
    {"id": "Maithili", "text": "Maithili"},
    {"id": "Malayalam", "text": "Malayalam"},
    {"id": "Marathi", "text": "Marathi"},
    {"id": "Meitei", "text": "Meitei"},
    {"id": "Nepali", "text": "Nepali"},
    {"id": "Nyishi", "text": "Nyishi"},
    {"id": "Odia", "text": "Odia"},
    {"id": "Punjabi", "text": "Punjabi"},
    {"id": "Santali", "text": "Santali"},
    {"id": "Tamil", "text": "Tamil"},
    {"id": "Telugu", "text": "Telugu"},
    {"id": "Toto", "text": "Toto"}
]
